{
    "1": {
        "name": "Raiders of the Lost Ark",
        "certificate": "PG",
        "runtime": "115 min",
        "genre": "Action, Adventure",
        "description": "In 1936, archaeologist and adventurer Indiana Jones is hired by the U.S. government to find the Ark of the Covenant before Adolf Hitler's Nazis can obtain its awesome powers.",
        "director": "",
        "stars": []
    },
    "2": {
        "name": "Excalibur",
        "certificate": "PG",
        "runtime": "140 min",
        "genre": "Adventure, Drama, Fantasy",
        "description": "Merlin the magician helps Arthur Pendragon unite the Britons around the Round Table of Camelot, even as dark forces conspire to tear it apart.",
        "director": "",
        "stars": []
    },
    "3": {
        "name": "Escape from New York",
        "certificate": "",
        "runtime": "99 min",
        "genre": "Action, Sci-Fi",
        "description": "In 1997, when the U.S. president crashes into Manhattan, now a giant maximum security prison, a convicted bank robber is sent in to rescue him.",
        "director": "",
        "stars": []
    },
    "4": {
        "name": "The Evil Dead",
        "certificate": "NC-17",
        "runtime": "85 min",
        "genre": "Horror",
        "description": "Five friends travel to a cabin in the woods, where they unknowingly release flesh-possessing demons.",
        "director": "",
        "stars": []
    },
    "5": {
        "name": "Das Boot",
        "certificate": "R",
        "runtime": "149 min",
        "genre": "Adventure, Drama, Thriller",
        "description": "The claustrophobic world of a WWII German U-boat; boredom, filth and sheer terror.",
        "director": "",
        "stars": []
    },
    "6": {
        "name": "On Golden Pond",
        "certificate": "",
        "runtime": "109 min",
        "genre": "Drama",
        "description": "Norman is a curmudgeon with an estranged relationship with his daughter Chelsea. At Golden Pond, he and his wife nevertheless agree to care for Billy, the son of Chelsea's new boyfriend, and a most unexpected relationship blooms.",
        "director": "",
        "stars": []
    },
    "7": {
        "name": "An American Werewolf in London",
        "certificate": "",
        "runtime": "97 min",
        "genre": "Comedy, Horror",
        "description": "Two American college students on a walking tour of Britain are attacked by a werewolf that none of the locals will admit exists.",
        "director": "",
        "stars": []
    },
    "8": {
        "name": "Mad Max 2",
        "certificate": "",
        "runtime": "95 min",
        "genre": "Action, Adventure, Sci-Fi",
        "description": "In the post-apocalyptic Australian wasteland, a cynical drifter agrees to help a small, gasoline rich community escape a horde of bandits.",
        "director": "",
        "stars": []
    },
    "9": {
        "name": "Porky's",
        "certificate": "",
        "runtime": "94 min",
        "genre": "Comedy",
        "description": "In 1954, a group of Florida high school students try to help their buddy lose his virginity, which leads them to seeking revenge on a sleazy nightclub owner and his redneck sheriff brother for harassing them.",
        "director": "",
        "stars": []
    },
    "10": {
        "name": "Friday the 13th Part 2",
        "certificate": "",
        "runtime": "87 min",
        "genre": "Horror, Mystery, Thriller",
        "description": "Mrs. Voorhees is dead, and Camp Crystal Lake is shut down, but a camp next to the infamous place is stalked by an unknown assailant.",
        "director": "",
        "stars": []
    },
    "11": {
        "name": "Clash of the Titans",
        "certificate": "",
        "runtime": "118 min",
        "genre": "Action, Adventure, Family",
        "description": "Perseus must battle Medusa and the Kraken to save the Princess Andromeda.",
        "director": "",
        "stars": []
    },
    "12": {
        "name": "Stripes",
        "certificate": "R",
        "runtime": "106 min",
        "genre": "Comedy, War",
        "description": "Two friends who are dissatisfied with their jobs decide to join the army for a bit of fun.",
        "director": "",
        "stars": []
    },
    "13": {
        "name": "Possession",
        "certificate": "",
        "runtime": "124 min",
        "genre": "Drama, Horror",
        "description": "A woman starts exhibiting increasingly disturbing behavior after asking her husband for a divorce. Suspicions of infidelity soon give way to something much more sinister.",
        "director": "",
        "stars": []
    },
    "14": {
        "name": "Body Heat",
        "certificate": "",
        "runtime": "113 min",
        "genre": "Crime, Drama, Romance",
        "description": "In the midst of a searing Florida heat wave, a woman persuades her lover, a small-town lawyer, to murder her rich husband.",
        "director": "",
        "stars": []
    },
    "15": {
        "name": "The Cannonball Run",
        "certificate": "",
        "runtime": "95 min",
        "genre": "Action, Comedy, Sport",
        "description": "A wide variety of eccentric competitors participate in a wild and illegal cross-country road race. However, the eccentric entrants will do anything to win the road race, including low-down, dirty tricks.",
        "director": "",
        "stars": []
    },
    "16": {
        "name": "Halloween II",
        "certificate": "",
        "runtime": "92 min",
        "genre": "Horror",
        "description": "While Sheriff Brackett and Dr. Loomis hunt for Michael Myers, a traumatized Laurie is rushed to hospital, and the serial killer is not far behind her.",
        "director": "",
        "stars": []
    },
    "17": {
        "name": "For Your Eyes Only",
        "certificate": "",
        "runtime": "127 min",
        "genre": "Action, Adventure, Thriller",
        "description": "Agent 007 is assigned to hunt for a lost British encryption device and prevent it from falling into enemy hands.",
        "director": "",
        "stars": []
    },
    "18": {
        "name": "Endless Love",
        "certificate": "",
        "runtime": "116 min",
        "genre": "Drama, Romance",
        "description": "A high school student's love for a 15-year-old girl is thwarted by parental disapproval, circumstance and accident.",
        "director": "",
        "stars": []
    },
    "19": {
        "name": "The Howling",
        "certificate": "",
        "runtime": "91 min",
        "genre": "Horror",
        "description": "After a bizarre and near deadly encounter with a serial killer, a television newswoman is sent to a remote mountain resort whose residents may not be what they seem.",
        "director": "",
        "stars": []
    },
    "20": {
        "name": "Heavy Metal",
        "certificate": "",
        "runtime": "86 min",
        "genre": "Animation, Adventure, Fantasy",
        "description": "A glowing green orb - which embodies ultimate evil - terrorizes a young girl with an anthology of bizarre and fantastic stories of dark fantasy, eroticism and horror.",
        "director": "",
        "stars": []
    },
    "21": {
        "name": "Time Bandits",
        "certificate": "",
        "runtime": "116 min",
        "genre": "Adventure, Comedy, Fantasy",
        "description": "A young boy accidentally joins a band of time travelling dwarves, as they jump from era to era looking for treasure to steal.",
        "director": "",
        "stars": []
    },
    "22": {
        "name": "Chariots of Fire",
        "certificate": "",
        "runtime": "125 min",
        "genre": "Biography, Drama, Sport",
        "description": "Two British track athletes, one a determined Jew, and the other a devout Christian, compete in the 1924 Olympics.",
        "director": "",
        "stars": []
    },
    "23": {
        "name": "Scanners",
        "certificate": "",
        "runtime": "103 min",
        "genre": "Horror, Sci-Fi, Thriller",
        "description": "A scientist sends a man with extraordinary psychic powers to hunt others like him.",
        "director": "",
        "stars": []
    },
    "24": {
        "name": "History of the World: Part I",
        "certificate": "",
        "runtime": "92 min",
        "genre": "Comedy, History",
        "description": "Mel Brooks brings his one-of-a-kind comic touch to the history of mankind covering events from the Old Testament to the French Revolution in a series of episodic comedy vignettes.",
        "director": "",
        "stars": []
    },
    "25": {
        "name": "The Fox and the Hound",
        "certificate": "",
        "runtime": "83 min",
        "genre": "Animation, Adventure, Drama",
        "description": "Two childhood friends find themselves forced to become enemies.",
        "director": "",
        "stars": []
    },
    "26": {
        "name": "Mommie Dearest",
        "certificate": "R",
        "runtime": "129 min",
        "genre": "Biography, Drama",
        "description": "The abusive and traumatic adoptive upbringing of Christina Crawford at the hands of her mother, screen queen Joan Crawford, is depicted.",
        "director": "",
        "stars": []
    },
    "27": {
        "name": "Eye of the Needle",
        "certificate": "",
        "runtime": "112 min",
        "genre": "Romance, Thriller, War",
        "description": "A ruthless German spy, trying to get out of Britain with vital information about D-Day, must spend time with a young woman and her crippled husband.",
        "director": "",
        "stars": []
    },
    "28": {
        "name": "Taps",
        "certificate": "",
        "runtime": "126 min",
        "genre": "Drama",
        "description": "Military cadets take extreme measures to insure the future of their academy when its existence is threatened by local condo developers.",
        "director": "",
        "stars": []
    },
    "29": {
        "name": "Blow Out",
        "certificate": "",
        "runtime": "108 min",
        "genre": "Mystery, Thriller",
        "description": "A movie sound recordist accidentally records the evidence that proves that a car accident was actually murder and consequently finds himself in danger.",
        "director": "",
        "stars": []
    },
    "30": {
        "name": "La guerre du feu",
        "certificate": "",
        "runtime": "100 min",
        "genre": "Adventure, Drama, History",
        "description": "This story takes place in prehistoric time when three tribesmen search for a new fire source.",
        "director": "",
        "stars": []
    },
    "31": {
        "name": "Christiane F. - Wir Kinder vom Bahnhof Zoo",
        "certificate": "",
        "runtime": "138 min",
        "genre": "Biography, Drama",
        "description": "This movie portrays the drug scene in Berlin in the 1970s, following tape recordings of Christiane F. 14-year-old Christiane lives with her mother and little sister in a typical multi-story...                See full summary\u00a0\u00bb",
        "director": "",
        "stars": []
    },
    "32": {
        "name": "The Four Seasons",
        "certificate": "",
        "runtime": "107 min",
        "genre": "Comedy, Drama",
        "description": "Three middle-aged wealthy couples take vacations together in Spring, Summer, Autumn and Winter. Along the way we are treated to mid-life, marital, parental and other crises.",
        "director": "",
        "stars": []
    },
    "33": {
        "name": "Outland",
        "certificate": "",
        "runtime": "109 min",
        "genre": "Action, Crime, Sci-Fi",
        "description": "In the distant future, a police marshal stationed at a remote mining colony on the Jupiter moon of Io uncovers a drug-smuggling conspiracy, and gets no help from the populace when he later finds himself marked for murder.",
        "director": "",
        "stars": []
    },
    "34": {
        "name": "Southern Comfort",
        "certificate": "",
        "runtime": "106 min",
        "genre": "Action, Thriller",
        "description": "During a routine exercise, a team of National Guards are threatened by angry and violent locals.",
        "director": "",
        "stars": []
    },
    "35": {
        "name": "The Burning",
        "certificate": "",
        "runtime": "91 min",
        "genre": "Horror",
        "description": "A former summer camp caretaker, horribly burned from a prank gone wrong, lurks around an upstate New York summer camp bent on killing the teenagers responsible for his disfigurement.",
        "director": "",
        "stars": []
    },
    "36": {
        "name": "Arthur",
        "certificate": "",
        "runtime": "97 min",
        "genre": "Comedy, Romance",
        "description": "Arthur is a happy drunk with no pretensions at any ambition. He is also the heir to a vast fortune which he is told will only be his if he marries Susan. He does not love Susan, but she ...                See full summary\u00a0\u00bb",
        "director": "",
        "stars": []
    },
    "37": {
        "name": "Dragonslayer",
        "certificate": "",
        "runtime": "108 min",
        "genre": "Action, Adventure, Fantasy",
        "description": "A young wizarding apprentice is sent to kill a dragon which has been devouring girls from a nearby kingdom.",
        "director": "",
        "stars": []
    },
    "38": {
        "name": "Ragtime",
        "certificate": "",
        "runtime": "155 min",
        "genre": "Drama",
        "description": "A young black pianist becomes embroiled in the lives of an upper-class white family set among the racial tensions, infidelity, violence, and other nostalgic events in early 1900s New York City.",
        "director": "",
        "stars": []
    },
    "39": {
        "name": "Reds",
        "certificate": "",
        "runtime": "195 min",
        "genre": "Biography, Drama, History",
        "description": "A radical American journalist becomes involved with the Communist revolution in Russia, and hopes to bring its spirit and idealism to the United States.",
        "director": "",
        "stars": []
    },
    "40": {
        "name": "Piranha Part Two: The Spawning",
        "certificate": "",
        "runtime": "94 min",
        "genre": "Drama, Horror, Romance",
        "description": "A scuba diving instructor, her biochemist boyfriend, and her police chief ex-husband try to link a series of bizarre deaths to a mutant strain of piranha fish whose lair is a sunken freighter ship off a Caribbean island resort.",
        "director": "",
        "stars": []
    },
    "41": {
        "name": "The Postman Always Rings Twice",
        "certificate": "",
        "runtime": "122 min",
        "genre": "Crime, Drama, Romance",
        "description": "The sensuous wife of a lunch wagon proprietor and a rootless drifter begin a sordidly steamy affair and conspire to murder her Greek husband.",
        "director": "",
        "stars": []
    },
    "42": {
        "name": "Thief",
        "certificate": "",
        "runtime": "123 min",
        "genre": "Action, Crime, Drama",
        "description": "Coming closer to his dream of leading a normal life, a professional safecracker agrees to do a job for the Mafia, who has other plans for him.",
        "director": "",
        "stars": []
    },
    "43": {
        "name": "Roar",
        "certificate": "",
        "runtime": "102 min",
        "genre": "Adventure, Thriller",
        "description": "A family goes to Africa to meet their father who lives with wild lions.",
        "director": "",
        "stars": []
    },
    "44": {
        "name": "True Confessions",
        "certificate": "",
        "runtime": "108 min",
        "genre": "Crime, Drama",
        "description": "A worldly ambitious monsignor clashes with his older brother, a cynical Los Angeles homicide detective who is investigating the brutal murder of a young prostitute.",
        "director": "",
        "stars": []
    },
    "45": {
        "name": "...E tu vivrai nel terrore! L'aldil\u00e0",
        "certificate": "",
        "runtime": "87 min",
        "genre": "Horror",
        "description": "A young woman inherits an old hotel in Louisiana where, following a series of supernatural \"accidents\", she learns that the building was built over one of the entrances to Hell.",
        "director": "",
        "stars": []
    },
    "46": {
        "name": "Gallipoli",
        "certificate": "",
        "runtime": "110 min",
        "genre": "Adventure, Drama, History",
        "description": "Two Australian sprinters face the brutal realities of war when they are sent to fight in the Gallipoli campaign in Turkey during World War I.",
        "director": "",
        "stars": []
    },
    "47": {
        "name": "Happy Birthday to Me",
        "certificate": "",
        "runtime": "111 min",
        "genre": "Horror, Mystery, Thriller",
        "description": "At the snobby Crawford Academy, Virginia's group of friends start to go missing years after horrible events that happened to her as a child around her birthday.",
        "director": "",
        "stars": []
    },
    "48": {
        "name": "Tarzan the Ape Man",
        "certificate": "",
        "runtime": "115 min",
        "genre": "Adventure, Drama",
        "description": "While on an African expedition with her father, Jane Parker meets Tarzan, and the two become fascinated by each other.",
        "director": "",
        "stars": []
    },
    "49": {
        "name": "My Bloody Valentine",
        "certificate": "",
        "runtime": "90 min",
        "genre": "Horror, Mystery, Thriller",
        "description": "A decades-old folk tale surrounding a deranged murderer killing those who celebrate Valentine's Day turns out to be true to legend when a group defies the killer's order and people start turning up dead.",
        "director": "",
        "stars": []
    },
    "50": {
        "name": "Galaxy of Terror",
        "certificate": "",
        "runtime": "81 min",
        "genre": "Action, Adventure, Horror",
        "description": "Science fiction suspense thriller, in which a rescue space ship crew meets up with horrors projected by their own imaginations.",
        "director": "",
        "stars": []
    }
}
