{
    "1": {
        "name": "Hocus Pocus",
        "certificate": "PG",
        "runtime": "96 min",
        "genre": "Comedy, Family, Fantasy",
        "description": "A curious youngster moves to Salem, where he struggles to fit in before awakening a trio of diabolical witches that were executed in the 17th century.",
        "director": "",
        "stars": []
    },
    "2": {
        "name": "Addams Family Values",
        "certificate": "PG-13",
        "runtime": "94 min",
        "genre": "Comedy, Fantasy",
        "description": "The Addams Family try to rescue their beloved uncle Fester from his gold-digging new love, a black widow named Debbie.",
        "director": "",
        "stars": []
    },
    "3": {
        "name": "The Nightmare Before Christmas",
        "certificate": "PG",
        "runtime": "76 min",
        "genre": "Animation, Family, Fantasy",
        "description": "Jack Skellington, king of Halloween Town, discovers Christmas Town, but his attempts to bring Christmas to his home causes confusion.",
        "director": "",
        "stars": []
    },
    "4": {
        "name": "Dazed and Confused",
        "certificate": "R",
        "runtime": "102 min",
        "genre": "Comedy",
        "description": "The adventures of high school and junior high students on the last day of school in May 1976.",
        "director": "",
        "stars": []
    },
    "5": {
        "name": "Schindler's List",
        "certificate": "A",
        "runtime": "195 min",
        "genre": "Biography, Drama, History",
        "description": "In German-occupied Poland during World War II, industrialist Oskar Schindler gradually becomes concerned for his Jewish workforce after witnessing their persecution by the Nazis.",
        "director": "",
        "stars": []
    },
    "6": {
        "name": "Jurassic Park",
        "certificate": "UA",
        "runtime": "127 min",
        "genre": "Action, Adventure, Sci-Fi",
        "description": "A pragmatic Paleontologist visiting an almost complete theme park is tasked with protecting a couple of kids after a power failure causes the park's cloned dinosaurs to run loose.",
        "director": "",
        "stars": []
    },
    "7": {
        "name": "Tombstone",
        "certificate": "R",
        "runtime": "130 min",
        "genre": "Action, Biography, Drama",
        "description": "A successful lawman's plans to retire anonymously in Tombstone, Arizona, are disrupted by the kind of outlaws he was famous for eliminating.",
        "director": "",
        "stars": []
    },
    "8": {
        "name": "True Romance",
        "certificate": "R",
        "runtime": "119 min",
        "genre": "Crime, Drama, Romance",
        "description": "In Detroit, a lonely pop culture geek marries a call girl, steals cocaine from her pimp, and tries to sell it in Hollywood. Meanwhile, the owners of the cocaine, the Mob, track them down in an attempt to reclaim it.",
        "director": "",
        "stars": []
    },
    "9": {
        "name": "The Fugitive",
        "certificate": "PG-13",
        "runtime": "130 min",
        "genre": "Action, Crime, Drama",
        "description": "Dr. Richard Kimble, unjustly accused of murdering his wife, must find the real killer while being the target of a nationwide manhunt led by a seasoned U.S. Marshal.",
        "director": "",
        "stars": []
    },
    "10": {
        "name": "Mrs. Doubtfire",
        "certificate": "PG-13",
        "runtime": "125 min",
        "genre": "Comedy, Drama, Family",
        "description": "After a bitter divorce, an actor disguises himself as a female housekeeper to spend time with his children held in custody by his former wife.",
        "director": "",
        "stars": []
    },
    "11": {
        "name": "A Bronx Tale",
        "certificate": "R",
        "runtime": "121 min",
        "genre": "Crime, Drama, Romance",
        "description": "A father becomes worried when a local gangster befriends his son in the Bronx in the 1960s.",
        "director": "",
        "stars": []
    },
    "12": {
        "name": "What's Eating Gilbert Grape",
        "certificate": "PG-13",
        "runtime": "118 min",
        "genre": "Drama",
        "description": "After his father's death, Gilbert has to care for his mentally-disabled brother, Arnie, and his morbidly obese mother. This situation is suddenly challenged though, when love unexpectedly walks into his life.",
        "director": "",
        "stars": []
    },
    "13": {
        "name": "Indecent Proposal",
        "certificate": "R",
        "runtime": "117 min",
        "genre": "Drama, Romance",
        "description": "A billionaire offers one million dollars to a young married couple for one night with the wife.",
        "director": "",
        "stars": []
    },
    "14": {
        "name": "The Piano",
        "certificate": "R",
        "runtime": "121 min",
        "genre": "Drama, Music, Romance",
        "description": "A mute woman is sent to 1850s New Zealand along with her young daughter and prized piano for an arranged marriage to a wealthy landowner, but is soon lusted after by a local worker on the plantation.",
        "director": "",
        "stars": []
    },
    "15": {
        "name": "The Age of Innocence",
        "certificate": "PG",
        "runtime": "139 min",
        "genre": "Drama, Romance",
        "description": "A tale of nineteenth-century New York high society in which a young lawyer falls in love with a woman separated from her husband, while he is engaged to the woman's cousin.",
        "director": "",
        "stars": []
    },
    "16": {
        "name": "Groundhog Day",
        "certificate": "PG",
        "runtime": "101 min",
        "genre": "Comedy, Fantasy, Romance",
        "description": "A weatherman finds himself inexplicably living the same day over and over again.",
        "director": "",
        "stars": []
    },
    "17": {
        "name": "Robin Hood: Men in Tights",
        "certificate": "PG-13",
        "runtime": "104 min",
        "genre": "Adventure, Comedy, Musical",
        "description": "A spoof of Robin Hood in general, and Robin Hood: Prince of Thieves (1991) in particular.",
        "director": "",
        "stars": []
    },
    "18": {
        "name": "Falling Down",
        "certificate": "R",
        "runtime": "113 min",
        "genre": "Crime, Drama, Thriller",
        "description": "An unemployed defense worker frustrated with the various flaws he sees in society, begins to psychotically and violently lash out against them.",
        "director": "",
        "stars": []
    },
    "19": {
        "name": "Demolition Man",
        "certificate": "R",
        "runtime": "115 min",
        "genre": "Action, Crime, Sci-Fi",
        "description": "A police officer is brought out of suspended animation in prison to pursue an old ultra-violent nemesis who is loose in a non-violent future society.",
        "director": "",
        "stars": []
    },
    "20": {
        "name": "The Sandlot",
        "certificate": "PG",
        "runtime": "101 min",
        "genre": "Comedy, Drama, Family",
        "description": "In the summer of 1962, a new kid in town is taken under the wing of a young baseball prodigy and his rowdy team, resulting in many adventures.",
        "director": "",
        "stars": []
    },
    "21": {
        "name": "Philadelphia",
        "certificate": "PG-13",
        "runtime": "125 min",
        "genre": "Drama",
        "description": "When a man with HIV is fired by his law firm because of his condition, he hires a homophobic small time lawyer as the only willing advocate for a wrongful dismissal suit.",
        "director": "",
        "stars": []
    },
    "22": {
        "name": "Rudy",
        "certificate": "PG",
        "runtime": "114 min",
        "genre": "Biography, Drama, Sport",
        "description": "Rudy has always been told that he was too small to play college football. But he is determined to overcome the odds and fulfill his dream of playing for Notre Dame.",
        "director": "",
        "stars": []
    },
    "23": {
        "name": "The Firm",
        "certificate": "R",
        "runtime": "154 min",
        "genre": "Drama, Mystery, Thriller",
        "description": "A young lawyer joins a prestigious law firm only to discover that it has a sinister dark side.",
        "director": "",
        "stars": []
    },
    "24": {
        "name": "Bound by Honor",
        "certificate": "R",
        "runtime": "180 min",
        "genre": "Crime, Drama",
        "description": "Based on the true life experiences of poet Jimmy Santiago Baca, the film focuses on step-brothers Paco and Cruz, and their bi-racial cousin Miklo.",
        "director": "",
        "stars": []
    },
    "25": {
        "name": "Last Action Hero",
        "certificate": "PG-13",
        "runtime": "130 min",
        "genre": "Action, Adventure, Comedy",
        "description": "With the help of a magic ticket, a young movie fan is transported into the fictional world of his favorite action movie character.",
        "director": "",
        "stars": []
    },
    "26": {
        "name": "Super Mario Bros.",
        "certificate": "PG",
        "runtime": "104 min",
        "genre": "Adventure, Comedy, Family",
        "description": "Two Brooklyn plumbers, Mario and Luigi, must travel to another dimension to rescue a princess from the evil dictator King Koopa and stop him from taking over the world.",
        "director": "",
        "stars": []
    },
    "27": {
        "name": "The Remains of the Day",
        "certificate": "PG",
        "runtime": "134 min",
        "genre": "Drama, Romance",
        "description": "A butler who sacrificed body and soul to service in the years leading up to World War II realizes too late how misguided his loyalty was to his lordly employer.",
        "director": "",
        "stars": []
    },
    "28": {
        "name": "Naked",
        "certificate": "",
        "runtime": "132 min",
        "genre": "Comedy, Drama",
        "description": "Parallel tales of two sexually obsessed men, one hurting and annoying women physically and mentally, one wandering around the city talking to strangers and experiencing dimensions of life.",
        "director": "",
        "stars": []
    },
    "29": {
        "name": "Free Willy",
        "certificate": "PG",
        "runtime": "112 min",
        "genre": "Adventure, Drama, Family",
        "description": "When a boy learns that a beloved killer whale is to be killed by the aquarium owners, the boy risks everything to free the whale.",
        "director": "",
        "stars": []
    },
    "30": {
        "name": "Carlito's Way",
        "certificate": "R",
        "runtime": "144 min",
        "genre": "Crime, Drama, Thriller",
        "description": "A Puerto Rican former convict, just released from prison, pledges to stay away from drugs and violence despite the pressure around him and lead on to a better life outside of N.Y.C.",
        "director": "",
        "stars": []
    },
    "31": {
        "name": "Cliffhanger",
        "certificate": "R",
        "runtime": "113 min",
        "genre": "Action, Adventure, Thriller",
        "description": "A botched mid-air heist results in suitcases full of cash being searched for by various groups throughout the Rocky Mountains.",
        "director": "",
        "stars": []
    },
    "32": {
        "name": "Sleepless in Seattle",
        "certificate": "PG",
        "runtime": "105 min",
        "genre": "Comedy, Drama, Romance",
        "description": "A recently widowed man's son calls a radio talk-show in an attempt to find his father a partner.",
        "director": "",
        "stars": []
    },
    "33": {
        "name": "The Secret Garden",
        "certificate": "",
        "runtime": "101 min",
        "genre": "Drama, Family, Fantasy",
        "description": "A young, recently-orphaned girl is sent to England after living in India all her life. Once there, she begins to explore her new, seemingly-isolated surroundings -- and its secrets.",
        "director": "",
        "stars": []
    },
    "34": {
        "name": "In the Name of the Father",
        "certificate": "R",
        "runtime": "133 min",
        "genre": "Biography, Drama",
        "description": "A man's coerced confession to an IRA bombing he did not commit results in the imprisonment of his father as well. An English lawyer fights to free them.",
        "director": "",
        "stars": []
    },
    "35": {
        "name": "In the Line of Fire",
        "certificate": "R",
        "runtime": "128 min",
        "genre": "Action, Crime, Drama",
        "description": "Secret Service agent Frank Horrigan couldn't save Kennedy, but he's determined not to let a clever assassin take out this president.",
        "director": "",
        "stars": []
    },
    "36": {
        "name": "Sliver",
        "certificate": "R",
        "runtime": "107 min",
        "genre": "Drama, Thriller",
        "description": "A woman moves into an exclusive New York City apartment building, which she soon discovers houses tenants with all manner of shocking secrets.",
        "director": "",
        "stars": []
    },
    "37": {
        "name": "The Three Musketeers",
        "certificate": "PG",
        "runtime": "105 min",
        "genre": "Action, Adventure, Comedy",
        "description": "France, 1625: Young d'Artagnan heads to Paris to join the Musketeers but the evil cardinal's disbanded them - save 3. He meets the 3, Athos, Porthos and Aramis, and joins them on their quest to save the king and country.",
        "director": "",
        "stars": []
    },
    "38": {
        "name": "Homeward Bound: The Incredible Journey",
        "certificate": "",
        "runtime": "84 min",
        "genre": "Adventure, Comedy, Drama",
        "description": "Three pets escape from a California ranch to find their owners in San Francisco.",
        "director": "",
        "stars": []
    },
    "39": {
        "name": "The Crush",
        "certificate": "R",
        "runtime": "89 min",
        "genre": "Drama, Thriller",
        "description": "A journalist becomes the unwanted center of attention for a 14-year-old girl, who proceeds to sabotage his life after he refuses her sexual advances.",
        "director": "",
        "stars": []
    },
    "40": {
        "name": "Coneheads",
        "certificate": "PG",
        "runtime": "88 min",
        "genre": "Comedy, Sci-Fi",
        "description": "Aliens with conical crania crash-land on Earth.",
        "director": "",
        "stars": []
    },
    "41": {
        "name": "Leprechaun",
        "certificate": "R",
        "runtime": "92 min",
        "genre": "Comedy, Fantasy, Horror",
        "description": "An evil, sadistic Leprechaun goes on a killing rampage in search of his beloved pot of gold.",
        "director": "",
        "stars": []
    },
    "42": {
        "name": "Menace II Society",
        "certificate": "R",
        "runtime": "97 min",
        "genre": "Crime, Drama, Thriller",
        "description": "A young street hustler attempts to escape the rigors and temptations of the ghetto in a quest for a better life.",
        "director": "",
        "stars": []
    },
    "43": {
        "name": "Much Ado About Nothing",
        "certificate": "PG-13",
        "runtime": "111 min",
        "genre": "Comedy, Drama, Romance",
        "description": "Young lovers Hero and Claudio, soon to wed, conspire to get verbal sparring partners and confirmed singles Benedick and Beatrice to wed as well.",
        "director": "",
        "stars": []
    },
    "44": {
        "name": "Fire in the Sky",
        "certificate": "PG-13",
        "runtime": "109 min",
        "genre": "Biography, Drama, Fantasy",
        "description": "An Arizona logger mysteriously disappears for five days in an alleged encounter with a flying saucer in 1975.",
        "director": "",
        "stars": []
    },
    "45": {
        "name": "Dennis the Menace",
        "certificate": "PG",
        "runtime": "94 min",
        "genre": "Comedy, Family",
        "description": "When his parents have to go out of town, Dennis stays with Mr. and Mrs. Wilson. The little menace is driving Mr. Wilson crazy, but Dennis is just trying to be helpful. Even to the thief who's arrived in town.",
        "director": "",
        "stars": []
    },
    "46": {
        "name": "Alive",
        "certificate": "R",
        "runtime": "120 min",
        "genre": "Adventure, Biography, Drama",
        "description": "A Uruguayan rugby team stranded in the snow swept Andes are forced to use desperate measures to survive after a plane crash.",
        "director": "",
        "stars": []
    },
    "47": {
        "name": "Sister Act 2: Back in the Habit",
        "certificate": "PG",
        "runtime": "107 min",
        "genre": "Comedy, Family, Music",
        "description": "Showgirl Deloris Van Cartier returns as Sister Mary Clarence to teach music to a group of Catholic students whose run-down school is slated for closure.",
        "director": "",
        "stars": []
    },
    "48": {
        "name": "So I Married an Axe Murderer",
        "certificate": "PG-13",
        "runtime": "93 min",
        "genre": "Comedy, Romance",
        "description": "A San Francisco poet who fears commitment suspects his girlfriend may have a knack for killing off her significant others.",
        "director": "",
        "stars": []
    },
    "49": {
        "name": "Gettysburg",
        "certificate": "PG",
        "runtime": "271 min",
        "genre": "Drama, History, War",
        "description": "In 1863, the Northern and Southern forces fight at Gettysburg in the decisive battle of the American Civil War.",
        "director": "",
        "stars": []
    },
    "50": {
        "name": "Return of the Living Dead III",
        "certificate": "R",
        "runtime": "97 min",
        "genre": "Horror",
        "description": "Having recently witnessed the horrific results of a top secret project to bring the dead back to life, a distraught youth performs the operation on his girlfriend after she's killed in a motorcycle accident.",
        "director": "",
        "stars": []
    }
}
